README.rst
setup.cfg
setup.py
redis_sa/__init__.py
redis_sa/sniffer.py
redis_sa.egg-info/PKG-INFO
redis_sa.egg-info/SOURCES.txt
redis_sa.egg-info/dependency_links.txt
redis_sa.egg-info/entry_points.txt
redis_sa.egg-info/not-zip-safe
redis_sa.egg-info/requires.txt
redis_sa.egg-info/top_level.txt