Metadata-Version: 1.1
Name: redis-sa
Version: 0.1
Summary: A redis sniffer & analyzer
Home-page: https://github.com/xupeng/redis-sa
Author: Xupeng Yun
Author-email: xupeng@xupeng.me
License: MIT
Platform: UNKNOWN
Classifier: Topic :: Database
Classifier: Topic :: Utilities
Classifier: Topic :: System :: Systems Administration
Classifier: Programming Language :: Python
